deboiler/__init__.py
deboiler/deboiler.py
deboiler/logger.py
deboiler/lxml_query.py
deboiler/dataset/__init__.py
deboiler/dataset/avro_dataset.py
deboiler/dataset/base.py
deboiler/dataset/dataframe_dataset.py
deboiler/dataset/json_dataset.py
deboiler/dataset/list_dataset.py
deboiler/models/__init__.py
deboiler/models/lxml_node.py
deboiler/models/page.py
deboiler/models/tag.py
deboiler/tests/__init__.py
deboiler/tests/test_denoising.py
deboiler/tests/test_end_to_end_pipeline.py
deboiler/tests/test_language_detection.py
deboiler/tests/test_operation_modes.py
deboiler/tests/test_text_extraction.py
deboiler/tests/fixtures/__init__.py
deboiler-2023.46.150.dist-info/LICENSE
deboiler-2023.46.150.dist-info/METADATA
deboiler-2023.46.150.dist-info/WHEEL
deboiler-2023.46.150.dist-info/top_level.txt
deboiler-2023.46.150.dist-info/RECORD
